<?xml version="1.0" encoding="Windows-1252"?>
<LevelList xmlns:xsi="http://www.w3.org/2001/XMLSchema-instance" xmlns:xsd="http://www.w3.org/2001/XMLSchema">
  <Levels>
	  
	<!--TUTORIALS-->
    <Level>
      <displayName>0</displayName>
      <sceneName>Tutorial1</sceneName>
      <difficulty>0</difficulty>
      <subjectText>Level 1 - Linking I</subjectText>
      <messageText>Mission text coming soon!</messageText>
      <isPrimary>true</isPrimary>
      <senderName>Dr. Raoul Fernandez</senderName>
      <howToUnlock>NONE</howToUnlock>
      <rankRequirement>0</rankRequirement>
      <missionRequirementIndex>0</missionRequirementIndex>
      <contactRequirement></contactRequirement>
    </Level>
	
	 <Level>
      <displayName>0</displayName>
      <sceneName>Tutorial2</sceneName>
      <difficulty>0</difficulty>
      <subjectText>Level 2 - Linking II</subjectText>
      <messageText>Mission text coming soon!</messageText>
      <isPrimary>true</isPrimary>
      <senderName>Dr. Raoul Fernandez</senderName>
      <howToUnlock>MISSION</howToUnlock>
      <rankRequirement>0</rankRequirement>
      <missionRequirementIndex>0</missionRequirementIndex>
      <contactRequirement></contactRequirement>
    </Level>
	
	 <Level>
      <displayName>0</displayName>
      <sceneName>Tutorial3</sceneName>
      <difficulty>0</difficulty>
      <subjectText>Level 3 - Linking III</subjectText>
      <messageText>Mission text coming soon!</messageText>
      <isPrimary>true</isPrimary>
      <senderName>Dr. Raoul Fernandez</senderName>
      <howToUnlock>MISSION</howToUnlock>
      <rankRequirement>0</rankRequirement>
      <missionRequirementIndex>0</missionRequirementIndex>
      <contactRequirement></contactRequirement>
    </Level>
	
	<Level>
      <displayName>2</displayName>
      <sceneName>KU04</sceneName>
      <difficulty>0</difficulty>
      <subjectText>Level 5</subjectText>
      <messageText>Mission text coming soon!</messageText>
      <isPrimary>true</isPrimary>
      <senderName>Dr. Raoul Fernandez</senderName>
      <howToUnlock>MISSION</howToUnlock>
      <rankRequirement>0</rankRequirement>
      <missionRequirementIndex>1</missionRequirementIndex>
      <contactRequirement></contactRequirement>
    </Level>
	
	<Level>
      <displayName>3</displayName>
      <sceneName>RV14</sceneName>
      <difficulty>0</difficulty>
      <subjectText>Level 6 - Secondary Objectives</subjectText>
      <messageText>Mission text coming soon!</messageText>
      <isPrimary>true</isPrimary>
      <senderName>Dr. Raoul Fernandez</senderName>
      <howToUnlock>MISSION</howToUnlock>
      <rankRequirement>0</rankRequirement>
      <missionRequirementIndex>2</missionRequirementIndex>
      <contactRequirement></contactRequirement>
    </Level>
	
	<Level>
      <displayName>4</displayName>
      <sceneName>RV15</sceneName> <!--- > FIX THIS LATER!!!</!-->
      <difficulty>0</difficulty>
      <subjectText>Level 7 - Mutual Links</subjectText>
      <messageText> Mission text coming soon! </messageText>
      <isPrimary>true</isPrimary>
      <senderName>Dr. Raoul Fernandez</senderName>
      <howToUnlock>MISSION</howToUnlock>
      <rankRequirement>0</rankRequirement>
      <missionRequirementIndex>3</missionRequirementIndex>
      <contactRequirement></contactRequirement>
    </Level>
	
	<Level>
      <displayName>5</displayName>
      <sceneName>RV16</sceneName> <!--- > FIX THIS LATER!!!</!-->
      <difficulty>0</difficulty>
      <subjectText>Level 8</subjectText>
      <messageText> Mission text coming soon! </messageText>
      <isPrimary>true</isPrimary>
      <senderName>Dr. Raoul Fernandez</senderName>
      <howToUnlock>MISSION</howToUnlock>
      <rankRequirement>0</rankRequirement>
      <missionRequirementIndex>4</missionRequirementIndex>
      <contactRequirement></contactRequirement>
    </Level>
	
	<Level>
      <displayName>6</displayName>
      <sceneName>RV17</sceneName> <!--- > FIX THIS LATER!!!</!-->
      <difficulty>0</difficulty>
      <subjectText>Level 9</subjectText>
      <messageText> Mission text coming soon! </messageText>
      <isPrimary>true</isPrimary>
      <senderName>Dr. Raoul Fernandez</senderName>
      <howToUnlock>MISSION</howToUnlock>
      <rankRequirement>0</rankRequirement>
      <missionRequirementIndex>5</missionRequirementIndex>
      <contactRequirement></contactRequirement>
    </Level>
	
	<Level>
      <displayName>7</displayName>
      <sceneName>Tutorial5</sceneName> <!--- > FIX THIS LATER!!!</!-->
      <difficulty>0</difficulty>
      <subjectText>Level 10 - Engineer I</subjectText>
      <messageText> Mission text coming soon! </messageText>
      <isPrimary>true</isPrimary>
      <senderName>Dr. Raoul Fernandez</senderName>
      <howToUnlock>MISSION</howToUnlock>
      <rankRequirement>0</rankRequirement>
      <missionRequirementIndex>6</missionRequirementIndex>
      <contactRequirement></contactRequirement>
    </Level>
	
	<Level>
      <displayName>8</displayName>
      <sceneName>Tutorial6</sceneName> <!--- > FIX THIS LATER!!!</!-->
      <difficulty>0</difficulty>
      <subjectText>Level 11 - Engineer II</subjectText>
      <messageText> Mission text coming soon! </messageText>
      <isPrimary>true</isPrimary>
      <senderName>Dr. Raoul Fernandez</senderName>
      <howToUnlock>MISSION</howToUnlock>
      <rankRequirement>0</rankRequirement>
      <missionRequirementIndex>7</missionRequirementIndex>
      <contactRequirement></contactRequirement>
    </Level>
	
	<Level>
      <displayName>9</displayName>
      <sceneName>GPC07</sceneName> <!--- > FIX THIS LATER!!!</!-->
      <difficulty>0</difficulty>
      <subjectText>Level 12</subjectText>
      <messageText> Mission text coming soon! </messageText>
      <isPrimary>true</isPrimary>
      <senderName>Dr. Raoul Fernandez</senderName>
      <howToUnlock>MISSION</howToUnlock>
      <rankRequirement>0</rankRequirement>
      <missionRequirementIndex>8</missionRequirementIndex>
      <contactRequirement></contactRequirement>
    </Level>
	
	<Level>
      <displayName>10</displayName>
      <sceneName>GPC02</sceneName> <!--- > FIX THIS LATER!!!</!-->
      <difficulty>0</difficulty>
      <subjectText>Level 13</subjectText>
      <messageText> Mission text coming soon! </messageText>
      <isPrimary>true</isPrimary>
      <senderName>Dr. Raoul Fernandez</senderName>
      <howToUnlock>MISSION</howToUnlock>
      <rankRequirement>0</rankRequirement>
      <missionRequirementIndex>9</missionRequirementIndex>
      <contactRequirement></contactRequirement>
    </Level>
	
	
	<Level>
      <displayName>11</displayName>
      <sceneName>RV09</sceneName> <!--- > FIX THIS LATER!!!</!-->
      <difficulty>0</difficulty>
      <subjectText>Level 14</subjectText>
      <messageText> Mission text coming soon! </messageText>
      <isPrimary>true</isPrimary>
      <senderName>Dr. Raoul Fernandez</senderName>
      <howToUnlock>MISSION</howToUnlock>
      <rankRequirement>0</rankRequirement>
      <missionRequirementIndex>10</missionRequirementIndex>
      <contactRequirement></contactRequirement>
    </Level>
	
	<Level>
      <displayName>1</displayName>
      <sceneName>GPC05</sceneName>
      <difficulty>0</difficulty>
      <subjectText>Level 4</subjectText>
      <messageText>Mission text coming soon!</messageText>
      <isPrimary>true</isPrimary>
      <senderName>Dr. Raoul Fernandez</senderName>
      <howToUnlock>MISSION</howToUnlock>
      <rankRequirement>0</rankRequirement>
      <missionRequirementIndex>1</missionRequirementIndex>
      <contactRequirement></contactRequirement>
    </Level>
	
	<Level>
      <displayName>12</displayName>
      <sceneName>KU02</sceneName> <!--- > FIX THIS LATER!!!</!-->
      <difficulty>0</difficulty>
      <subjectText>Level 15</subjectText>
      <messageText> Mission text coming soon! </messageText>
      <isPrimary>true</isPrimary>
      <senderName>Dr. Raoul Fernandez</senderName>
      <howToUnlock>MISSION</howToUnlock>
      <rankRequirement>0</rankRequirement>
      <missionRequirementIndex>11</missionRequirementIndex>
      <contactRequirement></contactRequirement>
    </Level>
	
	<Level>
      <displayName>13</displayName>
      <sceneName>GPC03</sceneName> <!--- > FIX THIS LATER!!!</!-->
      <difficulty>0</difficulty>
      <subjectText>Level 16</subjectText>
      <messageText> Mission text coming soon! </messageText>
      <isPrimary>true</isPrimary>
      <senderName>Dr. Raoul Fernandez</senderName>
      <howToUnlock>MISSION</howToUnlock>
      <rankRequirement>0</rankRequirement>
      <missionRequirementIndex>12</missionRequirementIndex>
      <contactRequirement></contactRequirement>
    </Level>
	
	<Level>
      <displayName>14</displayName>
      <sceneName>Tutorial4</sceneName> <!--- > FIX THIS LATER!!!</!-->
      <difficulty>0</difficulty>
      <subjectText>Level 17 - Building Sites</subjectText>
      <messageText> Mission text coming soon! </messageText>
      <isPrimary>true</isPrimary>
      <senderName>Dr. Raoul Fernandez</senderName>
      <howToUnlock>MISSION</howToUnlock>
      <rankRequirement>0</rankRequirement>
      <missionRequirementIndex>13</missionRequirementIndex>
      <contactRequirement></contactRequirement>
    </Level>
		
	<Level>
      <displayName>15</displayName>
      <sceneName>GPC06</sceneName> <!--- > FIX THIS LATER!!!</!-->
      <difficulty>0</difficulty>
      <subjectText>Level 18</subjectText>
      <messageText> Mission text coming soon! </messageText>
      <isPrimary>true</isPrimary>
      <senderName>Dr. Raoul Fernandez</senderName>
      <howToUnlock>MISSION</howToUnlock>
      <rankRequirement>0</rankRequirement>
      <missionRequirementIndex>14</missionRequirementIndex>
      <contactRequirement></contactRequirement>
    </Level>
	
	<Level>
      <displayName>16</displayName>
      <sceneName>GPC09</sceneName> <!--- > FIX THIS LATER!!!</!-->
      <difficulty>1</difficulty>
      <subjectText>Level 19</subjectText>
      <messageText> Mission text coming soon! </messageText>
      <isPrimary>true</isPrimary>
      <senderName>Dr. Raoul Fernandez</senderName>
      <howToUnlock>MISSION</howToUnlock>
      <rankRequirement>0</rankRequirement>
      <missionRequirementIndex>15</missionRequirementIndex>
      <contactRequirement></contactRequirement>
    </Level>
	
	<Level>
      <displayName>17</displayName>
      <sceneName>RV02</sceneName> <!--- > FIX THIS LATER!!!</!-->
      <difficulty>1</difficulty>
      <subjectText>Level 20</subjectText>
      <messageText> Mission text coming soon! </messageText>
      <isPrimary>true</isPrimary>
      <senderName>Dr. Raoul Fernandez</senderName>
      <howToUnlock>MISSION</howToUnlock>
      <rankRequirement>0</rankRequirement>
      <missionRequirementIndex>16</missionRequirementIndex>
      <contactRequirement></contactRequirement>
    </Level>
		
	
	<Level>
      <displayName>18</displayName>
      <sceneName>RV01</sceneName> <!--- > FIX THIS LATER!!!</!-->
      <difficulty>1</difficulty>
      <subjectText>Level 21</subjectText>
      <messageText> Mission text coming soon! </messageText>
      <isPrimary>true</isPrimary>
      <senderName>Dr. Raoul Fernandez</senderName>
      <howToUnlock>MISSION</howToUnlock>
      <rankRequirement>0</rankRequirement>
      <missionRequirementIndex>17</missionRequirementIndex>
      <contactRequirement></contactRequirement>
    </Level>
	
	<Level>
      <displayName>19</displayName>
      <sceneName>RV04</sceneName> <!--- > FIX THIS LATER!!!</!-->
      <difficulty>1</difficulty>
      <subjectText>Level 22</subjectText>
      <messageText> Mission text coming soon! </messageText>
      <isPrimary>true</isPrimary>
      <senderName>Dr. Raoul Fernandez</senderName>
      <howToUnlock>MISSION</howToUnlock>
      <rankRequirement>0</rankRequirement>
      <missionRequirementIndex>18</missionRequirementIndex>
      <contactRequirement></contactRequirement>
    </Level>
	
	<Level>
      <displayName>20</displayName>
      <sceneName>RV22</sceneName> <!--- > FIX THIS LATER!!!</!-->
      <difficulty>1</difficulty>
      <subjectText>Level 23</subjectText>
      <messageText> Mission text coming soon! </messageText>
      <isPrimary>true</isPrimary>
      <senderName>Dr. Raoul Fernandez</senderName>
      <howToUnlock>MISSION</howToUnlock>
      <rankRequirement>0</rankRequirement>
      <missionRequirementIndex>19</missionRequirementIndex>
      <contactRequirement></contactRequirement>
    </Level>
	
	<Level>
      <displayName>21</displayName>
      <sceneName>RV23</sceneName> <!--- > FIX THIS LATER!!!</!-->
      <difficulty>0</difficulty>
      <subjectText>Level 24</subjectText>
      <messageText> Mission text coming soon! </messageText>
      <isPrimary>true</isPrimary>
      <senderName>Dr. Raoul Fernandez</senderName>
      <howToUnlock>MISSION</howToUnlock>
      <rankRequirement>0</rankRequirement>
      <missionRequirementIndex>20</missionRequirementIndex>
      <contactRequirement></contactRequirement>
    </Level>
	
	<Level>
      <displayName>22</displayName>
      <sceneName>GPC04</sceneName> <!--- > FIX THIS LATER!!!</!-->
      <difficulty>1</difficulty>
      <subjectText>Level 25</subjectText>
      <messageText> Mission text coming soon! </messageText>
      <isPrimary>true</isPrimary>
      <senderName>Dr. Raoul Fernandez</senderName>
      <howToUnlock>MISSION</howToUnlock>
      <rankRequirement>0</rankRequirement>
      <missionRequirementIndex>21</missionRequirementIndex>
      <contactRequirement></contactRequirement>
    </Level>
	
	<Level>
      <displayName>23</displayName>
      <sceneName>GPC08</sceneName> <!--- > FIX THIS LATER!!!</!-->
      <difficulty>1</difficulty>
      <subjectText>Level 26 - Agents</subjectText>
      <messageText> Mission text coming soon! </messageText>
      <isPrimary>true</isPrimary>
      <senderName>Dr. Raoul Fernandez</senderName>
      <howToUnlock>MISSION</howToUnlock>
      <rankRequirement>0</rankRequirement>
      <missionRequirementIndex>22</missionRequirementIndex>
      <contactRequirement></contactRequirement>
    </Level>
	
	<Level>
      <displayName>24</displayName>
      <sceneName>DD08-2</sceneName> <!--- > FIX THIS LATER!!!</!-->
      <difficulty>1</difficulty>
      <subjectText>Level 27</subjectText>
      <messageText> Mission text coming soon! </messageText>
      <isPrimary>true</isPrimary>
      <senderName>Dr. Raoul Fernandez</senderName>
      <howToUnlock>MISSION</howToUnlock>
      <rankRequirement>0</rankRequirement>
      <missionRequirementIndex>23</missionRequirementIndex>
      <contactRequirement></contactRequirement>
    </Level>
	
	<Level>
      <displayName>25</displayName>
      <sceneName>DD10</sceneName> <!--- > FIX THIS LATER!!!</!-->
      <difficulty>1</difficulty>
      <subjectText>Level 28</subjectText>
      <messageText> Mission text coming soon! </messageText>
      <isPrimary>true</isPrimary>
      <senderName>Dr. Raoul Fernandez</senderName>
      <howToUnlock>MISSION</howToUnlock>
      <rankRequirement>0</rankRequirement>
      <missionRequirementIndex>24</missionRequirementIndex>
      <contactRequirement></contactRequirement>
    </Level>
	
	<Level>
      <displayName>26</displayName>
      <sceneName>KU-02</sceneName> <!--- > FIX THIS LATER!!!</!-->
      <difficulty>1</difficulty>
      <subjectText>Level 29</subjectText>
      <messageText> Mission text coming soon! </messageText>
      <isPrimary>true</isPrimary>
      <senderName>Dr. Raoul Fernandez</senderName>
      <howToUnlock>MISSION</howToUnlock>
      <rankRequirement>0</rankRequirement>
      <missionRequirementIndex>25</missionRequirementIndex>
      <contactRequirement></contactRequirement>
    </Level>
	
	<Level>
      <displayName>27</displayName>
      <sceneName>GPC01</sceneName> <!--- > FIX THIS LATER!!!</!-->
      <difficulty>2</difficulty>
      <subjectText>Level 30</subjectText>
      <messageText> Mission text coming soon! </messageText>
      <isPrimary>true</isPrimary>
      <senderName>Dr. Raoul Fernandez</senderName>
      <howToUnlock>MISSION</howToUnlock>
      <rankRequirement>0</rankRequirement>
      <missionRequirementIndex>26</missionRequirementIndex>
      <contactRequirement></contactRequirement>
    </Level>
	
	<Level>
      <displayName>28</displayName>
      <sceneName>KU-03</sceneName> <!--- > FIX THIS LATER!!!</!-->
      <difficulty>0</difficulty>
      <subjectText>Level 31</subjectText>
      <messageText> Mission text coming soon! </messageText>
      <isPrimary>true</isPrimary>
      <senderName>Dr. Raoul Fernandez</senderName>
      <howToUnlock>MISSION</howToUnlock>
      <rankRequirement>0</rankRequirement>
      <missionRequirementIndex>27</missionRequirementIndex>
      <contactRequirement></contactRequirement>
    </Level>
		
  </Levels>
</LevelList>